MANIFEST.in
README.md
README.rst
setup.cfg
setup.py
WebOb_GraphQL.egg-info/PKG-INFO
WebOb_GraphQL.egg-info/SOURCES.txt
WebOb_GraphQL.egg-info/dependency_links.txt
WebOb_GraphQL.egg-info/not-zip-safe
WebOb_GraphQL.egg-info/requires.txt
WebOb_GraphQL.egg-info/top_level.txt
webob_graphql/__init__.py
webob_graphql/base.py
webob_graphql/mako.py
webob_graphql/render_graphiql.py
webob_graphql/utils.py