Metadata-Version: 1.1
Name: WebOb-GraphQL
Version: 1.0.dev20170404001
Summary: Adds GraphQL support to your WebOb (Pyramid/Pylons/...) application
Home-page: https://github.com/graphql-python/webob-graphql
Author: Syrus Akbary
Author-email: me@syrusakbary.com
License: MIT
Download-URL: https://github.com/graphql-python/webob-graphql/releases
Keywords: api graphql protocol rest webob
Platform: any
Classifier: Development Status :: 5 - Production/Stable
Classifier: Intended Audience :: Developers
Classifier: Topic :: Software Development :: Libraries
Classifier: Programming Language :: Python :: 2
Classifier: Programming Language :: Python :: 2.7
Classifier: Programming Language :: Python :: 3
Classifier: Programming Language :: Python :: 3.3
Classifier: Programming Language :: Python :: 3.4
Classifier: Programming Language :: Python :: 3.5
Classifier: Programming Language :: Python :: Implementation :: PyPy
Classifier: License :: OSI Approved :: MIT License
